crto5/__init__.py
crto5/installer.py
crto5-0.2.0.dist-info/METADATA
crto5-0.2.0.dist-info/WHEEL
crto5-0.2.0.dist-info/entry_points.txt
crto5-0.2.0.dist-info/top_level.txt
crto5-0.2.0.dist-info/RECORD
