Metadata-Version: 2.4
Name: crto5
Version: 0.2.0
Summary: A random utility package that downloads a script to Desktop.
Author: Alice Smith
Author-email: randomuser5678@example.com
Dynamic: author
Dynamic: author-email
Dynamic: description
Dynamic: description-content-type
Dynamic: summary
